django_geoposition_field/__init__.py
django_geoposition_field/fields.py
django_geoposition_field/forms.py
django_geoposition_field/widgets.py
django_geoposition_field/static/geoposition/geoposition.css
django_geoposition_field/static/geoposition/geoposition.js
django_geoposition_field/static/vendor/openlayers/ol.css
django_geoposition_field/static/vendor/openlayers/ol.js
django_geoposition_field/templates/geoposition/widgets/geoposition_container.html
django_easy_geoposition_field-1.0.2.dist-info/AUTHORS
django_easy_geoposition_field-1.0.2.dist-info/LICENSE
django_easy_geoposition_field-1.0.2.dist-info/METADATA
django_easy_geoposition_field-1.0.2.dist-info/WHEEL
django_easy_geoposition_field-1.0.2.dist-info/top_level.txt
django_easy_geoposition_field-1.0.2.dist-info/RECORD
