Metadata-Version: 2.1
Name: django-easy-geoposition-field
Version: 1.0.2
Summary: Django simple geoposition field with OSM widget
Author-email: Miroslav Bendík <miroslav.bendik@gmail.com>
License: MIT
Project-URL: homepage, https://github.com/mireq/django-geoposition-field
Project-URL: documentation, https://github.com/mireq/django-geoposition-field
Project-URL: repository, https://github.com/mireq/django-geoposition-field
Project-URL: changelog, https://github.com/mireq/django-geoposition-field/blob/master/CHANGELOG.md
Keywords: geoposition,widget,django,field
Classifier: Programming Language :: Python :: 3
Requires-Python: >=3.7
License-File: LICENSE
License-File: AUTHORS
Requires-Dist: django
Provides-Extra: dev
Requires-Dist: tox ; extra == 'dev'
Requires-Dist: pylint ; extra == 'dev'
Requires-Dist: pre-commit ; extra == 'dev'
Requires-Dist: bump2version ; extra == 'dev'
Requires-Dist: commitizen ; extra == 'dev'
Requires-Dist: django-jinja ; extra == 'dev'
